python_package_14721/__init__.py
python_package_14721/calculation.py
python_package_14721-0.0.2.dist-info/METADATA
python_package_14721-0.0.2.dist-info/WHEEL
python_package_14721-0.0.2.dist-info/top_level.txt
python_package_14721-0.0.2.dist-info/RECORD
