Metadata-Version: 2.4
Name: python_package_14721
Version: 0.0.2
Summary: A test python package for class assignment
Dynamic: description
Dynamic: description-content-type
Dynamic: summary
